rmftool/__init__.py
rmftool/het_refinedRefined_transientRegime.py
rmftool/population_processes.py
rmftool/refinedRefined_fixedPoint.py
rmftool/refinedRefined_transientRegime.py
rmftool-0.5.dist-info/LICENSE
rmftool-0.5.dist-info/METADATA
rmftool-0.5.dist-info/WHEEL
rmftool-0.5.dist-info/top_level.txt
rmftool-0.5.dist-info/RECORD
