Metadata-Version: 2.1
Name: rmftool
Version: 0.5
Summary: A library to Compute (Refined) Mean Field Approximations
Home-page: https://github.com/ngast/rmf_tool
Author: Nicolas Gast
Author-email: nicolas.gast@inria.fr
License: UNKNOWN
Project-URL: Bug Tracker, https://github.com/ngast/rmf_tool/issues
Platform: UNKNOWN
Classifier: Programming Language :: Python :: 3
Classifier: Operating System :: OS Independent
Classifier: License :: OSI Approved :: MIT License
Requires-Python: >=3.6
License-File: LICENSE
